peregrin/__init__.py
peregrin/scripts.py
peregrin-0.0.3.dist-info/METADATA
peregrin-0.0.3.dist-info/WHEEL
peregrin-0.0.3.dist-info/top_level.txt
peregrin-0.0.3.dist-info/RECORD
